webfaster/__init__.py
webfaster/webfaster.py
webfaster-0.1.1.dist-info/licenses/LICENSE
webfaster-0.1.1.dist-info/METADATA
webfaster-0.1.1.dist-info/WHEEL
webfaster-0.1.1.dist-info/top_level.txt
webfaster-0.1.1.dist-info/RECORD
